aicard/__init__.py
aicard/agents/__init__.py
aicard/agents/agent.py
aicard/agents/gpt.py
aicard/agents/ollama.py
aicard/card/__init__.py
aicard/card/dot_dict.py
aicard/card/model_card.py
aicard/card/traits/__init__.py
aicard/card/traits/html.py
aicard/card/traits/metrics.py
aicard/card/traits/plots.py
aicard/card/traits/repo.py
aicard/card/traits/version_control.py
aicard/evaluation/__init__.py
aicard/evaluation/experiments.py
aicard/evaluation/loaders.py
aicard/evaluation/metrics.py
aicard/evaluation/params.py
aicard/evaluation/task.py
aicard/evaluation/sid/__init__.py
aicard/evaluation/sid/_evaluation.py
aicard/evaluation/std/__init__.py
aicard/evaluation/std/_evaluation.py
aicard/evaluation/tasks/__init__.py
aicard/evaluation/tasks/multimodal.py
aicard/evaluation/tasks/nlp.py
aicard/evaluation/tasks/vision.py
aicard/explainers/__init__.py
aicard/explainers/shap/__init__.py
aicard/explainers/shap/image/__init__.py
aicard/explainers/shap/image/classification/__init__.py
aicard/explainers/shap/image/classification/_explainer.py
aicard/explainers/shap/text/__init__.py
aicard/explainers/shap/text/classification/__init__.py
aicard/explainers/shap/text/classification/_explainer.py
aicard/service/__init__.py
aicard/service/assistant.py
aicard/service/client.py
aicard/service/converters.py
aicard/service/logger.py
aicard/service/server.py
aicard/service/users.py
aicard/utils/__init__.py
aicard/utils/_count_data.py
aicard/utils/_extract_dataset_info.py
aicard/utils/_read_data_structure.py
aicard/utils/emission.py
aicard/utils/hr_sw_info.py
aicard/utils/model_info.py
aicard-0.3.3.dist-info/METADATA
aicard-0.3.3.dist-info/WHEEL
aicard-0.3.3.dist-info/top_level.txt
aicard-0.3.3.dist-info/RECORD
