Metadata-Version: 2.4
Name: aicard
Version: 0.3.3
Summary: Compute and organize model cards locally or online.
Home-page: https://github.com/mever-team/transparency-service
Author: CERTH
Author-email: gnikoul@gmail.com
Classifier: Programming Language :: Python :: 3
Classifier: License :: OSI Approved :: MIT License
Classifier: Operating System :: OS Independent
Classifier: Intended Audience :: Developers
Classifier: Development Status :: 3 - Alpha
Requires-Python: >=3.11
Requires-Dist: PyGithub
Requires-Dist: openai
Requires-Dist: PyPDF2
Requires-Dist: pandas
Requires-Dist: matplotlib
Requires-Dist: markdown
Requires-Dist: shap
Requires-Dist: ipython
Requires-Dist: gdown
Requires-Dist: plotly
Requires-Dist: transformers
Requires-Dist: accelerate>=0.26.0
Requires-Dist: validators
Requires-Dist: datasets
Requires-Dist: torch
Requires-Dist: torchmetrics
Requires-Dist: eco2ai
Requires-Dist: GPUtil
Requires-Dist: kagglehub
Requires-Dist: html2text
Requires-Dist: markdown2
Requires-Dist: rich
Requires-Dist: flask
Requires-Dist: flasgger
Requires-Dist: bcrypt
Requires-Dist: python-dotenv
Dynamic: author
Dynamic: author-email
Dynamic: classifier
Dynamic: description
Dynamic: description-content-type
Dynamic: home-page
Dynamic: requires-dist
Dynamic: requires-python
Dynamic: summary
